sql/__init__.py
sql/postgre_sql.py
t_commenter-0.1.1.dist-info/LICENSE
t_commenter-0.1.1.dist-info/METADATA
t_commenter-0.1.1.dist-info/WHEEL
t_commenter-0.1.1.dist-info/top_level.txt
t_commenter-0.1.1.dist-info/RECORD
