Metadata-Version: 2.2
Name: t-commenter
Version: 0.1.1
Summary: A module for working with table metadata (comments on tables, views, materialized views, and columns) in PostgreSQL.
Author-email: ArtemXYZ <poznyshev.a.a@yandex.ru>
License: MIT License
Project-URL: Repository, https://github.com/ArtemXYZ/t-commenter.git
Project-URL: Issues, https://github.com/ArtemXYZ/t-commenter/issues
Project-URL: Changelog, https://github.com/ArtemXYZ/t-commenter/blob/main/CHANGELOG.md
Keywords: comments on tables,tables,views,materialized views,columns,PostgreSQL,t-commenter,SQLAlchemy,create comments on tables,objects in a database,T-COMMENTER,DAGs,airflow,Airflow,Table Commentator,set table comment,get table comments,set column comment
Classifier: Development Status :: 5 - Production/Stable
Classifier: Intended Audience :: Developers
Classifier: Topic :: Database
Classifier: Topic :: Database :: Database Engines/Servers
Classifier: Topic :: Software Development
Classifier: Programming Language :: Python :: 3
Classifier: Operating System :: OS Independent
Classifier: License :: OSI Approved :: MIT License
Requires-Python: <4.0,>=3.8
License-File: LICENSE
Requires-Dist: SQLAlchemy<3.0.0,>=2.0.37
Requires-Dist: psycopg2-binary<3.0.0,>=2.9.0
Provides-Extra: dev
Requires-Dist: pytest<9.0.0,>=8.3.4; extra == "dev"
